README.md
setup.py
pipeline_dsl/__init__.py
pipeline_dsl/shell.py
pipeline_dsl.egg-info/PKG-INFO
pipeline_dsl.egg-info/SOURCES.txt
pipeline_dsl.egg-info/dependency_links.txt
pipeline_dsl.egg-info/requires.txt
pipeline_dsl.egg-info/top_level.txt
pipeline_dsl/concourse/__init__.py
pipeline_dsl/concourse/__shared.py
pipeline_dsl/concourse/job.py
pipeline_dsl/concourse/pipeline.py
pipeline_dsl/concourse/task.py
pipeline_dsl/resources/__init__.py
pipeline_dsl/resources/cron.py
pipeline_dsl/resources/docker.py
pipeline_dsl/resources/gcs.py
pipeline_dsl/resources/git.py
pipeline_dsl/resources/github.py
pipeline_dsl/resources/github_pr.py
pipeline_dsl/resources/pool.py
pipeline_dsl/resources/pypi.py
pipeline_dsl/resources/registry_image.py
pipeline_dsl/resources/semver.py
pipeline_dsl/test/__init__.py
pipeline_dsl/test/test_job.py
pipeline_dsl/test/test_pipeline.py
pipeline_dsl/test/test_resource.py
pipeline_dsl/test/test_task.py
pipeline_dsl/utils/__init__.py
pipeline_dsl/utils/docker_daemon.py
pipeline_dsl/utils/modify_git_repo.py