Metadata-Version: 2.1
Name: pipeline-dsl
Version: 0.3.0
Summary: A Python Pipeline DSL for Concourse
Home-page: https://github.com/SAP/pipeline-dsl
Author: SAP SE
Author-email: istio@sap.com
License: UNKNOWN
Platform: UNKNOWN
Classifier: Programming Language :: Python :: 3
Classifier: License :: OSI Approved :: Apache Software License
Classifier: Operating System :: OS Independent
Requires-Python: >=3.6
